{
  "version": "3.2.4",
  "generated_at": "2026-07-16T16:44:11Z",
  "daily": [
    {
      "title": "반년 만에 뒤집힌 AI 검색 왕좌…한국인, 챗GPT 대신 제미나이 택하기 시작했다",
      "source": "지디넷코리아",
      "link": "https://zdnet.co.kr/view/?no=20260716210925",
      "publishedAt": "Thu, 16 Jul 2026 12:09:25 GMT",
      "date": "2026-07-16",
      "category": "genai",
      "bullets": [
        "생성형 AI 검색은 이제 소수의 얼리어답터가 아니라 검색 이용자 절반 이상이 쓰는 주류 도구가 됐다.",
        "오픈서베이 조사에서 최근 3개월 안에 챗GPT를 검색에 써봤다는 응답은 58.1%, 제미나이는 52.2%에 달했다.",
        "특히 제미나이는 반년 전보다 이용 경험이 23.3%p나 급증하며 전체 검색 서비스 상위 5위 안에 진입했다."
      ],
      "contentVerified": true
    },
    {
      "title": "사이냅소프트, 65억원 규모 법제처 ‘생성형 AI 법령검색 시스템 구축’ 사업 참여",
      "source": "디지털경제뉴스",
      "link": "https://www.denews.co.kr/news/articleView.html?idxno=41812",
      "publishedAt": "Thu, 16 Jul 2026 10:56:07 GMT",
      "date": "2026-07-16",
      "category": "genai",
      "bullets": [
        "​​​​​​​​​[디지털경제뉴스 박시현 기자] 사이냅소프트는 법제처의 ‘생성형 AI 법령검색 시스템 구축’ 사업에 참여한다고 밝혔다.",
        "이번 사업은 주관사인 코난테크놀로지를 비롯해 사이냅소프트를 포함한 총 4개 사가 컨소시엄을 구성해 수주했다.",
        "총 사업 규모는 65억 5000만 원으로, 지난 5월 29일 정식 계약을 체결했다."
      ],
      "contentVerified": true
    },
    {
      "title": "사이냅소프트, 법제처 '생성형 AI 법령검색 시스템 구축' 참여",
      "source": "디일렉",
      "link": "https://www.thelec.kr/news/articleView.html?idxno=59696",
      "publishedAt": "Thu, 16 Jul 2026 09:11:50 GMT",
      "date": "2026-07-16",
      "category": "genai",
      "bullets": [
        "도큐먼트 인공지능(AI) 기업 사이냅소프트가 법제처의 '생성형 AI 법령검색 시스템 구축'사업에 참여한다.",
        "이 사업의 주관사는 코난테크놀로지이며 사이냅소프트 등 4개사가 컨소시엄을 구성해 수주했다.",
        "내년 11월 완료 예정인 해당 사업은 기존 국가법령정보센터의 단어 유사도 매칭 방식과 수작업 데이터 구축의 한계를 극복하기 위해 추진하는 것이다."
      ],
      "contentVerified": true
    },
    {
      "title": "모니터랩, 생성형 AI 보안 ‘젠AI 시큐리티’ 고도화",
      "source": "아이티데일리",
      "link": "https://www.itdaily.kr/news/articleView.html?idxno=240439",
      "publishedAt": "Thu, 16 Jul 2026 08:21:50 GMT",
      "date": "2026-07-16",
      "category": "genai",
      "bullets": [
        "[아이티데일리]모니터랩은 생성형 인공지능(AI) 보안 솔루션 ‘젠AI 시큐리티(GenAI Security)’를 고도화했다고 16일 밝혔다.",
        "젠AI 시큐리티는 생성형 AI 활용 과정에서 발생할 수 있는 프롬프트 인젝션, AI 오용, 민감정보 유출을 방지하는 솔루션이다.",
        "정밀한 위협 분류와 맞춤형 보안 정책이 고도화의 핵심이다."
      ],
      "contentVerified": true
    },
    {
      "title": "\"소양강변에 AI 데이터센터 유치… 풍부한 물, 수도권 접근성 갖춰\"",
      "source": "조선일보",
      "link": "https://www.chosun.com/national/regional/2026/07/17/UTBD2B7IXVD3LPIS3GUVUOVXWA/",
      "publishedAt": "Thu, 16 Jul 2026 15:46:00 GMT",
      "date": "2026-07-17",
      "category": "biz",
      "bullets": [
        "육동한 강원 춘천시장이 춘천시청 집무실에서 본지와 인터뷰하고 있다.",
        "육 시장은 “소양강변에 AI 데이터센터를 유치해 춘천의 새로운 성장 동력으로 만들겠다”고 했다.",
        "“AI(인공지능) 시대에는 물이 경쟁력입니다."
      ],
      "contentVerified": true
    },
    {
      "title": "AI 못 넘볼 기술 배운다…용접·전기 찾는 청년들",
      "source": "더팩트",
      "link": "https://m.tf.co.kr/amp/life/2344390.htm",
      "publishedAt": "Thu, 16 Jul 2026 15:00:00 GMT",
      "date": "2026-07-17",
      "category": "biz",
      "bullets": [
        "취업난과 AI(인공지능) 확산에 따른 직무 환경 변화 속에서 용접, 전기 등 현장 기술을 배우려는 청년들이 늘고 있다.",
        "전문가들은 이 같은 현상을 취업 불안과 노동시장 변화에 대비하려는 청년들의 선택으로 보고 기술직 선호 흐름이 당분간 이어질 것으로 내다봤다.",
        "서울시 기술교육원은 청년층의 기술 교육 수요에 맞춰 올해 하반기부터 지게차운전 등 청년특화과정을 신설했다."
      ],
      "contentVerified": true
    },
    {
      "title": "투자만 있고 수익은 없는 AI 경고",
      "source": "블록미디어",
      "link": "https://www.blockmedia.co.kr/archives/1117864",
      "publishedAt": "Thu, 16 Jul 2026 14:31:00 GMT",
      "date": "2026-07-16",
      "category": "biz",
      "bullets": [
        "인공지능(AI) 산업에 투입되는 막대한 자본이 실적과 수익성으로 이어질 수 있는지를 둘러싼 의구심이 다시 커지고 있다.",
        "IBM과 아시아 반도체주가 급락하고 미국 주가지수 선물 과 비트코인 까지 약세를 보이면서 AI 거품 붕괴 가능성에 대한 시장의 경계가 확산됐다.",
        "16일(현지시각) 코인게이프에 따르면 폴리마켓에서 올해 AI 거품이 붕괴될 가능성은 18%를 넘어섰다."
      ],
      "contentVerified": true
    },
    {
      "title": "안양시, ‘인공지능(AI) 정책 자문단’ 출범",
      "source": "경기매일",
      "link": "https://www.kgmail.kr/news/articleView.html?idxno=632935",
      "publishedAt": "Thu, 16 Jul 2026 09:22:05 GMT",
      "date": "2026-07-16",
      "category": "biz",
      "bullets": [
        "16일 오후 4시 30분 스마트도시통합센터에서 열린 '안양시 인공지능(AI) 정책 자문단' 위촉식 및 제1차 회의에서 최대호 안양시장이 인사말을 하고 있다.",
        "[경기매일] 안양시는 시정 전반에 인공지능(AI) 기술을 접목하기 위한 '인공지능(AI) 정책 자문단'을 구성해 본격적인 활동에 나선다고 16일 밝혔다.",
        "시는 이날 오후 4시 30분 스마트도시통합센터에서 최대호 안양시장과 이계삼 부시장(자문단 위원장) 등 위원 14명이 참석한 가운데 ‘안양시 인공지능 정책 자문단 위촉식 및 제1차 회의’를 개최했다."
      ],
      "contentVerified": true
    },
    {
      "title": "中, 美 맞설 AI 국제기구 공식 출범…29개국 참여",
      "source": "데일리안",
      "link": "https://www.dailian.co.kr/news/view/1668181/%E4%B8%AD-%E7%BE%8E-%EB%A7%9E%EC%84%A4-AI-%EA%B5%AD%EC%A0%9C%EA%B8%B0%EA%B5%AC-%EA%B3%B5%EC%8B%9D-%EC%B6%9C%EB%B2%94-2026",
      "publishedAt": "Thu, 16 Jul 2026 16:03:00 GMT",
      "date": "2026-07-17",
      "category": "tech",
      "bullets": [
        "시진핑 중국 국가주석이 15일 상하이 황푸구의 한 주거지역을 둘러보고 있다.",
        "중국이 미국 중심의 인공지능(AI) 질서에 맞서 새로운 국제 협력기구를 공식 출범시키며 글로벌 AI 주도권 경쟁에 본격적으로 뛰어들었다.",
        "16일(현지시간) 로이터통신에 따르면 중국을 포함한 29개국은 이날 상하이에서 세계 AI 협력기구(WAICO) 설립 협정에 서명했다."
      ],
      "contentVerified": true
    },
    {
      "title": "루닛, 글로벌 AI 컨소시엄 합류로 신약개발 지원",
      "source": "데일리팜",
      "link": "https://www.dailypharm.com/user/news/340534",
      "publishedAt": "Thu, 16 Jul 2026 15:30:05 GMT",
      "date": "2026-07-17",
      "category": "tech",
      "bullets": [
        "약국대출 메디라이프 신규 개국을 앞두고 있습니다.",
        "루닛이 글로벌 디지털 병리·정밀진단 기업들과 손잡고 인공지능(AI) 기반 신약개발 지원 생태계에 합류한다.",
        "의료 인공지능 기업 루닛(대표 서범석)은 AI, 디지털 병리, 정밀진단 분야 글로벌 기업 8개사가 참여하는 신약개발 AI 컨소시엄에 합류했다고 16일 밝혔다."
      ],
      "contentVerified": true
    },
    {
      "title": "AI 로봇 글로벌 3강 도전 국가 프로젝트 시동 K-휴머노이드 시대 연다",
      "source": "gonggam.korea.kr",
      "link": "https://gonggam.korea.kr/newsContentView.es?mid=a12501000000&section_id=NCCD_POLICY_TOTAL&content=&code_cd=&nPage=2&b_list=9&news_id=fafb5b70-c8dc-40c8-b093-bbac7ee7176f",
      "publishedAt": "Thu, 16 Jul 2026 13:17:37 GMT",
      "date": "2026-07-16",
      "category": "tech",
      "bullets": [
        "정부가 인공지능(AI) 로봇을 차세대 국가 성장동력으로 육성하기 위한 대규모 프로젝트에 착수했다.",
        "제조업 혁신부터 핵심기술 확보, 양산 기반 구축까지 전 주기를 지원해 글로벌 AI 로봇 강국으로 도약하겠다는 구상이다.",
        "정부는 6월 발표한 ‘대한민국 대도약 3대 메가프로젝트’에서 AI 로봇 분야를 미래 성장동력으로 육성해 글로벌 3강으로 도약하겠다는 목표를 제시했다."
      ],
      "contentVerified": true
    },
    {
      "title": "일본, 독자 '로봇 AI 모델' 개발…엔비디아 루빈 2만7500개 도입 - 머니투데이",
      "source": "머니투데이",
      "link": "https://www.mt.co.kr/amp/world/2026/07/16/2026071617153221705",
      "publishedAt": "Thu, 16 Jul 2026 08:54:42 GMT",
      "date": "2026-07-16",
      "category": "tech",
      "bullets": [
        "일본에서 인공지능(AI) 주도권 확보를 위해 국가 차원의 소버린 AI 연합이 16일 공식 출범했다.",
        "엔비디아의 차세대 AI 반도체를 대규모로 확보해 '피지컬 AI' 개발에 나선단 계획이다.",
        "니혼게이자이와 블룸버그 등 주요 외신에 따르면 일본 경제산업성은 이날 도쿄에서 일본판 피지컬 AI 육성 계획을 공개했다."
      ],
      "contentVerified": true
    },
    {
      "title": "구글, EU 규정 따라 AI·검색 경쟁사에 서비스 개방해야",
      "source": "ESG비즈니스리뷰",
      "link": "https://www.esgbusinessreview.kr/news/articleView.html?idxno=6805",
      "publishedAt": "Thu, 16 Jul 2026 14:46:04 GMT",
      "date": "2026-07-16",
      "category": "policy",
      "bullets": [
        "빅테크의 시장 지배력 제한을 위한 디지털시장법(DMA·Digital Markets Act) 이행의 일환이다.",
        "구글의 최고법률책임자(CLO) 켄트 워커는 이메일 성명을 통해 \"오늘 발표된 결정은 수백만 유럽 이용자를 위한 중요한 개인정보 보호와 보안 장치를 약화시킬 위험이 있다\"고 주장했다.",
        "그는 이어 \"우리는 이용자를 보호하면서도 DMA의 목표를 충족할 수 있는 여러 해결책을 반복적으로 제안했지만, 이번 결정은 이용자 피해에 관한 광범위한 증거를 외면했다\"고 말했다."
      ],
      "contentVerified": true
    },
    {
      "title": "영국 법률 서비스위원회 \"AI 법률 도구, 규제 공백 속 소비자 무방비\" 공식 경고",
      "source": "뉴스N연합",
      "link": "https://newsyonhap.com/news/114486",
      "publishedAt": "Thu, 16 Jul 2026 12:30:14 GMT",
      "date": "2026-07-16",
      "category": "policy",
      "bullets": [
        "핵심 우려 사항은 AI 법률 도구를 직접 사용하는 소비자가 적절한 보호를 받지 못할 수 있다는 점이다.",
        "규제 변호사나 법률 회사를 통해 AI 지원을 받는 소비자는 전문적인 감독과 기존 구제 절차의 보호를 받는다.",
        "그러나 AI 법률 도구를 스스로 이용하는 소비자는 동등한 안전망을 갖추지 못한다."
      ],
      "contentVerified": true
    },
    {
      "title": "용량 제한 없는 ‘모두의 AI’ 전 국민에게 연내 무료 제공",
      "source": "부산일보",
      "link": "https://www.busan.com/view/busan/view.php?code=2026071618391568300",
      "publishedAt": "Thu, 16 Jul 2026 09:40:13 GMT",
      "date": "2026-07-16",
      "category": "policy",
      "bullets": [
        "배경훈(오른쪽) 부총리 겸 과기정통부 장관이 16일 부처 업무보고에서 발언하고 있다.",
        "이재명 대통령이 16일 청와대 영빈관에서 열린 국토부·과기부·해수부·방미통위·개보위 등에 대한 부처 업무보고를 주재하고 있다.",
        "정부가 전 국민이 우리 인공지능(AI)을 활용할 수 있도록 ‘모두의 AI’ 서비스를 출시한다."
      ],
      "contentVerified": true
    },
    {
      "title": "AI 시대의 권리와 법제도, 국민과 함께 논의… '2026 지능정보사회 법제도 포럼' 개최",
      "source": "로스쿨타임즈",
      "link": "https://www.lawschooltimes.com/news/articleView.html?idxno=11699",
      "publishedAt": "Thu, 16 Jul 2026 06:57:42 GMT",
      "date": "2026-07-16",
      "category": "policy",
      "bullets": [
        "한국지능정보사회진흥원(NIA)은 7월 23일 오후 1시 30분, 서울 포스트타워 명동 대회의실에서 ‘2026 지능정보사회 법제도 포럼 상반기 대국민 공개세미나’를 개최한다.",
        "‘AI와 우리의 일상-삶·권리·기회의 변화와 법제도 과제’를 주제로 열리는 이번 포럼은 인공지능(AI) 확산에 따른 사회 변화와 국민의 권리 보장, 법·제도 개선 방향을 논의하기 위해 마련됐다.",
        "개회식에 이어 김종철 방송미디어통신위원장이 ‘AI 기본사회와 국민주권 강화 방향’을 주제로 기조강연을 진행한다."
      ],
      "contentVerified": true
    }
  ],
  "weekly": [
    {
      "title": "제주도 안전건강실, '안전건강 AI 리더' 운영...업무 전반에 AI 활용",
      "source": "헤드라인제주",
      "link": "https://www.headlinejeju.co.kr/news/articleView.html?idxno=595991",
      "publishedAt": "Wed, 15 Jul 2026 06:03:00 GMT",
      "date": "2026-07-15",
      "category": "genai",
      "bullets": [
        "제주특별자치도 안전건강실 직원들이 생성형 인공지능(AI)을 행정 업무에 접목하는 학습 모임에 나서 주목된다.",
        "일정 관리·회의록 작성 같은 반복 업무는 AI에 맡겨 시간을 아끼고, 그 시간을 도민 안전 정책을 정교하게 다듬는 데 쓰겠다는 구상이다.",
        "제주도 안전건강실은 실무 담당자를 중심으로 꾸린 AI 학습 동아리 ‘안전건강 AI 리더’를 16일 1차 회의를 시작으로 본격 가동한다고 15일 밝혔다."
      ],
      "contentVerified": true
    },
    {
      "title": "제주도 안전건강실, 생성형 AI 학습모임 출범…행정업무 혁신 나선다",
      "source": "제주팟닷컴",
      "link": "https://jejupod.com/2026/07/15/jeju-ailearningclub/",
      "publishedAt": "Wed, 15 Jul 2026 04:40:36 GMT",
      "date": "2026-07-15",
      "category": "genai",
      "bullets": [
        "제주특별자치도 안전건강실이 생성형 인공지능(AI)을 행정업무에 적극 활용하기 위해 실무 중심의 AI 학습 동아리를 운영한다.",
        "반복 업무는 AI에 맡기고 확보한 시간을 도민 안전 정책 고도화에 활용한다는 구상이다.",
        "제주도 안전건강실은 실무 담당자 19명으로 구성된 AI 학습 동아리 ‘안전건강 AI 리더’를 16일 첫 회의를 시작으로 본격 운영한다고 밝혔다."
      ],
      "contentVerified": true
    },
    {
      "title": "사이냅소프트, 법제처 '생성형 AI 법령검색 시스템 구축' 사업 컨소시엄 참여",
      "source": "파이낸스스코프",
      "link": "https://www.finance-scope.com/article/view/scp202607160029",
      "publishedAt": "Thu, 16 Jul 2026 06:09:00 GMT",
      "date": "2026-07-16",
      "category": "genai",
      "bullets": [
        "국민 누구나 일상적인 문장으로 법령을 쉽게 검색할 수 있는 인공지능(AI) 기반 국가법령정보센터가 새롭게 구축된다.",
        "사이냅소프트는 16일 법제처의 '생성형 AI 법령검색 시스템 구축' 사업에 참여한다고 밝혔다.",
        "사이냅소프트는 주관사인 코난테크놀로지를 비롯한 총 4곳과 컨소시엄을 구성했다."
      ],
      "contentVerified": true
    },
    {
      "title": "루닛, 글로벌 8개社 '신약개발 AI 컨소시엄' 참여",
      "source": "바이오스펙테이터",
      "link": "https://www.biospectator.com/news/view/29319",
      "publishedAt": "Thu, 16 Jul 2026 01:05:00 GMT",
      "date": "2026-07-16",
      "category": "tech",
      "bullets": [
        "이 기사는 유료회원을 위한 BioS+ 기사입니다.",
        "의료 인공지능(AI) 기업 루닛(Lunit)은 AI와 디지털 병리, 정밀진단 분야의 글로벌 기업 8개사가 참여하는 '신약개발 AI 컨소시엄'에 합류했다고 16일 밝혔다.",
        "이번 컨소시엄은 글로벌 제약사가 환자 선별, 임상시험 운영, 동반진단(CDx) 개발 등 신약개발 전 과정에서의 AI 기반 병리분석과 바이오마커 개발역량을 강화하고, 신약개발을 가속화하기 위해 출범했다."
      ],
      "contentVerified": true
    },
    {
      "title": "트럼프 행정부, 중국산 오픈소스 AI 규제 '행정명령' 검토",
      "source": "AI타임스",
      "link": "https://www.aitimes.com/news/articleView.html?idxno=212674",
      "publishedAt": "Sun, 12 Jul 2026 03:57:09 GMT",
      "date": "2026-07-12",
      "category": "policy",
      "bullets": [
        "미국 트럼프 행정부가 중국산 오픈소스 AI 모델의 급속한 성장에 대응하기 위한 정책 검토에 착수한 것으로 알려졌다.",
        "아직 초기 논의 단계이지만, 중국 기업이 개발한 오픈소스 AI 모델의 정부 사용을 제한하는 행정명령 가능성까지 거론되고 있다.",
        "폴리티코는 10일(현지시간) 복수 관계자를 인용, 트럼프 행정부 관계자들이 기존 미국 정책으로는 충분히 대응하기 어려운 보안 위험을 초래할 수 있는 오픈소스 AI를 어떻게 규제할지 논의를 진행하고 있다고 보도했다."
      ],
      "contentVerified": true
    }
  ]
}
